{"_ts":[1559374422],"_r":{"breakdown":{"html":{"bytes":[3051],"requests":[1]},"js":{"bytes":[203691],"requests":[9]},"css":{"bytes":[0],"requests":[0]},"image":{"bytes":[1333],"requests":[3]},"flash":{"bytes":[0],"requests":[0]},"font":{"bytes":[71344],"requests":[3]},"video":{"bytes":[0],"requests":[0]},"other":{"bytes":[572],"requests":[2]}},"date":[1559374422],"domElements":[48],"domInteractive":[420],"firstPaint":[2023.2499999984],"fullyLoaded":[3056],"id":["190601_VB_9f80dc5a6325bf6bb87019b495a6a709"],"loadTime":[1151],"render":[2000],"SpeedIndex":[2000],"TTFB":[373],"videoFrames":[[{"_i":"ms_000000.jpg","_t":0,"_vc":0},{"_i":"ms_002000.jpg","_t":2000,"_vc":100}]],"visualComplete":[2000],"lighthouse":[54],"pagespeed":[96]}}